SeleniumLibraryToBrowser/__init__.py
SeleniumLibraryToBrowser/errors.py
SeleniumLibraryToBrowser/keys.py
SeleniumStats/__init__.py
SeleniumStats/__main__.py
robotframework_browser_migration-1.0.0.dist-info/METADATA
robotframework_browser_migration-1.0.0.dist-info/WHEEL
robotframework_browser_migration-1.0.0.dist-info/entry_points.txt
robotframework_browser_migration-1.0.0.dist-info/top_level.txt
robotframework_browser_migration-1.0.0.dist-info/RECORD
