Metadata-Version: 2.1
Name: robotframework-browser-migration
Version: 1.0.0
Summary: Some small helpers for migration of SeleniumLibrary to Browser
Home-page: https://github.com/Snooz82/robotframework-browser-migration
Author: René Rohner(Snooz82)
Author-email: snooz@posteo.de
Classifier: Programming Language :: Python :: 3
Classifier: Programming Language :: Python :: 3.6
Classifier: Programming Language :: Python :: 3.7
Classifier: Programming Language :: Python :: 3.8
Classifier: License :: OSI Approved :: Apache Software License
Classifier: Operating System :: OS Independent
Classifier: Topic :: Software Development :: Testing
Classifier: Topic :: Software Development :: Testing :: Acceptance
Classifier: Framework :: Robot Framework
Requires-Python: >=3.6
Requires-Dist: robotframework >=5.0
